{
  "statusCode": 200,
  "salesOrderVBO": [
    {
      "orderID": "3",
      "status": "DRAFT",
      "created": "2015-12-23T22:34:39",
      "createdBy": "ePOS",
      "lastModified": "2015-09-25T22:34:39",
      "count": 5,
      "details": {
        "contactInfo": "SalesAgent007",
        "callBackDate": "2015-09-26T22:34:39",
        "additionalNotes": "3 Orders Added"
      },
      "roles": {
        "agent": {
          "voID": "123456",
          "name": "Max Mustermann"
        },
        "customer": {
          "type": "privat"
        }
      },
      "parts": {
        "lineItems": [
          {
            "orderLineItemID": "1",
            "type": "Activation",
            "category": "prepaid",
            "status": "DRAFT",
            "lastModified": "2015-09-25T22:34:39",
            "orderDateTime": "2015-09-25T22:34:39",
            "productOffering": {
              "code": "VFREDL8GB",
              "name": "Vodafone RED 8GB Premium Smartphone",
              "specification": "tariff-group",
              "characteristicValue": [
                {
                  "name": "SubsidyLevel",
                  "value": "Subsidy 1"
                }
              ],
              "product": [
                {
                  "specification": "hardware",
                  "characteristicValue": [
                    {
                      "name": "IMEI for copy",
                      "value": "6543987654675431"
                    }
                  ]
                },
                {
                  "specification": "sim-card",
                  "characteristicValue": [
                    {
                      "name": "Pre registered phone number for copy",
                      "value": "10120410200031"
                    }
                  ]
                },
                {
                  "specification": "Optionen",
                  "count": 2
                },
                {
                  "specification": "Promotions",
                  "count": 0
                },
                {
                  "specification": "Rabatte",
                  "count": 2
                }
              ]
            }
          },
          {
            "orderLineItemID": "2",
            "type": "Activation Classic Porting",
            "category": "prepaid",
            "status": "SENT",
            "lastModified": "2015-09-25T22:34:39",
            "orderDateTime": "2015-09-25T22:34:39",
            "productOffering": {
              "code": "VFREDL6GB",
              "name": "Vodafone RED 6GB Premium Smartphone",
              "specification": "tariff-group",
              "characteristicValue": [
                {
                  "name": "SubsidyLevel",
                  "value": "Subsidy 2"
                }
              ],
              "product": [
                {
                  "specification": "hardware",
                  "characteristicValue": [
                    {
                      "name": "IMEI for copy",
                      "value": "6543987654675431"
                    }
                  ]
                },
                {
                  "specification": "sim-card",
                  "characteristicValue": [
                    {
                      "name": "SIM serial number for copy",
                      "value": "10120410200031"
                    }
                  ]
                },
                {
                  "specification": "Optionen",
                  "count": 2
                },
                {
                  "specification": "Promotions",
                  "count": 1
                },
                {
                  "specification": "Rabatte",
                  "count": 0
                }
              ]
            }
          },
          {
            "orderLineItemID": "3",
            "type": "Activation",
            "category": "singleItem",
            "status": "CONFIRMED",
            "lastModified": "2015-09-25T22:34:39",
            "orderDateTime": "2015-09-24T22:34:39",
            "productOffering": {
              "code": "VFREDL3GB",
              "name": "Vodafone RED 3GB",
              "specification": "tariff-group",
              "characteristicValue": [
                {
                  "name": "SubsidyLevel",
                  "value": "Subsidy 3"
                }
              ],
              "product": [
                {
                  "specification": "hardware",
                  "characteristicValue": [
                    {
                      "name": "IMEI for copy",
                      "value": "6543987654675431"
                    }
                  ]
                },
                {
                  "specification": "sim-card",
                  "characteristicValue": [
                    {
                      "name": "SIM serial number for copy",
                      "value": "10120410200031"
                    }
                  ]
                },
                {
                  "specification": "Optionen",
                  "count": 3
                },
                {
                  "specification": "Promotions",
                  "count": 2
                },
                {
                  "specification": "Rabatte",
                  "count": 3
                }
              ]
            }
          }

        ]
      }
    }
  ]
}

